ruranges/__init__.py
ruranges/ruranges.cpython-313-x86_64-linux-gnu.so
ruranges-0.0.14.dist-info/METADATA
ruranges-0.0.14.dist-info/WHEEL
ruranges-0.0.14.dist-info/RECORD
ruranges-0.0.14.dist-info/licenses/LICENSE
