Metadata-Version: 2.4
Name: ruranges
Version: 0.0.14
Classifier: Programming Language :: Python :: 3
Classifier: Programming Language :: Python :: 3.12
Classifier: Programming Language :: Rust
Classifier: License :: OSI Approved :: MIT License
Classifier: Operating System :: OS Independent
Requires-Dist: numpy
License-File: LICENSE
Requires-Python: >=3.12
Project-URL: Repository, https://github.com/pyranges/ruranges
